ccmanage/__init__.py
ccmanage/auth.py
ccmanage/lease.py
ccmanage/quicknode.py
ccmanage/secrets.py
ccmanage/server.py
ccmanage/ssh.py
ccmanage/util.py
hammers/__init__.py
hammers/colors.py
hammers/diagnostics.py
hammers/interactive.py
hammers/mycnf.py
hammers/mysqlargs.py
hammers/mysqlshim.py
hammers/osapi.py
hammers/query.py
hammers/slack.py
hammers/util.py
hammers/osrest/__init__.py
hammers/osrest/blazar.py
hammers/osrest/glance.py
hammers/osrest/ironic.py
hammers/osrest/keystone.py
hammers/osrest/neutron.py
hammers/osrest/nova.py
hammers/scripts/__init__.py
hammers/scripts/conflict_macs.py
hammers/scripts/curiouser.py
hammers/scripts/dirty_ports.py
hammers/scripts/ironic_error_resetter.py
hammers/scripts/maintenance_reservation.py
hammers/scripts/metadata_sync.py
hammers/scripts/neutron_reaper.py
hammers/scripts/orphan_resource_providers.py
hammers/scripts/undead_instances.py
hammers-0.2.0.dist-info/METADATA
hammers-0.2.0.dist-info/RECORD
hammers-0.2.0.dist-info/WHEEL
hammers-0.2.0.dist-info/entry_points.txt
hammers-0.2.0.dist-info/top_level.txt
