Metadata-Version: 2.1
Name: hammers
Version: 0.2.0
Summary: Bag of hammers to fix problems
Home-page: https://github.com/ChameleonCloud/hammers
Author: Nick Timkovich
Author-email: npt@uchicago.edu
License: UNKNOWN
Keywords: chameleon-cloud,chameleon,openstack
Platform: UNKNOWN
Classifier: Development Status :: 4 - Beta
Classifier: Environment :: OpenStack
Classifier: Intended Audience :: System Administrators
Classifier: Topic :: Utilities
Requires-Dist: python-dateutil
Requires-Dist: requests
